termcs/__init__.py
termcs/bottomWidget.py
termcs/screener.py
termcs/screenerTable.py
termcs/termcs.css
termcs/termcs.py
termcs/topWidget.py
termcs/utils.py
termcs/worker.py
termcs-0.1.4.dist-info/LICENSE
termcs-0.1.4.dist-info/METADATA
termcs-0.1.4.dist-info/WHEEL
termcs-0.1.4.dist-info/entry_points.txt
termcs-0.1.4.dist-info/top_level.txt
termcs-0.1.4.dist-info/RECORD
