Metadata-Version: 2.1
Name: termcs
Version: 0.1.4
Summary: Terminal crypto screener
Author: Riyum
License: Copyright (c) 2023 Riyum
Project-URL: Homepage, https://github.com/Riyum/termcs
Project-URL: Bug Tracker, https://github.com/Riyum/termcs/issues
Classifier: Environment :: Console
Classifier: Programming Language :: Python :: 3.7
Classifier: Programming Language :: Python :: 3.8
Classifier: Programming Language :: Python :: 3.9
Classifier: Programming Language :: Python :: 3.10
Classifier: Programming Language :: Python :: 3.11
Classifier: Operating System :: Microsoft :: Windows
Classifier: Operating System :: MacOS
Classifier: Operating System :: POSIX :: Linux
Classifier: License :: OSI Approved :: MIT License
Requires-Python: >=3.7.7
License-File: LICENSE
Requires-Dist: textual >=0.19.1
Requires-Dist: requests
Requires-Dist: websockets
